HISTORY.rst
LICENSE.rst
MANIFEST.in
Makefile
README.rst
setup.py
bin/.DS_Store
bin/excentury
docs/Makefile
docs/build/doctrees/armadillo.doctree
docs/build/doctrees/environment.pickle
docs/build/doctrees/excentury.doctree
docs/build/doctrees/format.doctree
docs/build/doctrees/index.doctree
docs/build/doctrees/installation.doctree
docs/build/doctrees/start.doctree
docs/build/doctrees/cpp/debug.doctree
docs/build/html/.buildinfo
docs/build/html/armadillo.html
docs/build/html/excentury.html
docs/build/html/format.html
docs/build/html/genindex.html
docs/build/html/index.html
docs/build/html/installation.html
docs/build/html/objects.inv
docs/build/html/search.html
docs/build/html/searchindex.js
docs/build/html/start.html
docs/build/html/_sources/armadillo.txt
docs/build/html/_sources/excentury.txt
docs/build/html/_sources/format.txt
docs/build/html/_sources/index.txt
docs/build/html/_sources/installation.txt
docs/build/html/_sources/start.txt
docs/build/html/_sources/cpp/debug.txt
docs/build/html/_static/ajax-loader.gif
docs/build/html/_static/basic.css
docs/build/html/_static/comment-bright.png
docs/build/html/_static/comment-close.png
docs/build/html/_static/comment.png
docs/build/html/_static/doctools.js
docs/build/html/_static/down-pressed.png
docs/build/html/_static/down.png
docs/build/html/_static/file.png
docs/build/html/_static/jquery.js
docs/build/html/_static/minus.png
docs/build/html/_static/plus.png
docs/build/html/_static/pygments.css
docs/build/html/_static/searchtools.js
docs/build/html/_static/underscore.js
docs/build/html/_static/up-pressed.png
docs/build/html/_static/up.png
docs/build/html/_static/websupport.js
docs/build/html/_static/css/badge_only.css
docs/build/html/_static/css/theme.css
docs/build/html/_static/fonts/fontawesome-webfont.eot
docs/build/html/_static/fonts/fontawesome-webfont.svg
docs/build/html/_static/fonts/fontawesome-webfont.ttf
docs/build/html/_static/fonts/fontawesome-webfont.woff
docs/build/html/_static/js/theme.js
excentury.egg-info/PKG-INFO
excentury.egg-info/SOURCES.txt
excentury.egg-info/dependency_links.txt
excentury.egg-info/requires.txt
excentury.egg-info/top_level.txt
