Metadata-Version: 1.1
Name: excentury
Version: 0.2.4
Summary: Call C++ from Python and MATLAB
Home-page: http://excentury.readthedocs.org
Author: Manuel Lopez
Author-email: jmlopez.rod@gmail.com
License: BSD License
Keywords: c++ python matlab interoperability
Platform: Darwin
Platform: Linux
Classifier: Development Status :: 5 - Production/Stable
Classifier: License :: OSI Approved :: BSD License
Classifier: Operating System :: MacOS :: MacOS X
Classifier: Operating System :: POSIX :: Linux
Classifier: Programming Language :: Python :: 2
Classifier: Topic :: Scientific/Engineering :: Mathematics
